django_uturn-0.3.1.dist-info/DESCRIPTION.rst
django_uturn-0.3.1.dist-info/LICENSE.txt
django_uturn-0.3.1.dist-info/METADATA
django_uturn-0.3.1.dist-info/pydist.json
django_uturn-0.3.1.dist-info/RECORD
django_uturn-0.3.1.dist-info/top_level.txt
django_uturn-0.3.1.dist-info/WHEEL
uturn/__init__.py
uturn/decorators.py
uturn/http.py
uturn/middleware.py
uturn/models.py
uturn/templatetags/__init__.py
uturn/templatetags/uturn.py
