Metadata-Version: 2.0
Name: django-uturn
Version: 0.3.1
Summary: Overriding redirects in Django, to return where you came from
Home-page: https://github.com/roam/django-uturn
Author: Kevin Wetzels
Author-email: kevin@roam.be
License: BSD
Platform: UNKNOWN
Classifier: Development Status :: 5 - Production/Stable
Classifier: Environment :: Web Environment
Classifier: Intended Audience :: Developers
Classifier: License :: OSI Approved :: BSD License
Classifier: Operating System :: OS Independent
Classifier: Programming Language :: Python
Classifier: Programming Language :: Python :: 2.6
Classifier: Programming Language :: Python :: 2.7
Classifier: Programming Language :: Python :: 3.2
Classifier: Programming Language :: Python :: 3.3
Requires-Dist: Django (>=1.4)
